attila/__init__.py
attila/__main__.py
attila/atcommand.py
attila/atcommunicator.py
attila/atre.py
attila/atresponse.py
attila/atscriptparser.py
attila/atsession.py
attila/esk.py
attila/exceptions.py
attila/virtual/__init__.py
attila/virtual/atvirtualcommunicator.py
attila/virtual/exceptions.py
attila/virtual/virtualserial.py
attila-1.2.2.dist-info/LICENSE
attila-1.2.2.dist-info/METADATA
attila-1.2.2.dist-info/WHEEL
attila-1.2.2.dist-info/entry_points.txt
attila-1.2.2.dist-info/top_level.txt
attila-1.2.2.dist-info/RECORD
