Metadata-Version: 2.1
Name: attila
Version: 1.2.2
Summary: Python module to communicate easily with modems and RF modules using AT commands
Home-page: https://github.com/veeso/ATtila
Author: Christian Visintin
Author-email: christian.visintin1997@gmail.com
License: MIT
Keywords: AT commands,IOT,wireless,radio frequency,modem,rf modules
Platform: UNKNOWN
Classifier: Development Status :: 5 - Production/Stable
Classifier: Intended Audience :: Developers
Classifier: Intended Audience :: Telecommunications Industry
Classifier: Intended Audience :: End Users/Desktop
Classifier: Topic :: Software Development :: Libraries
Classifier: Topic :: Home Automation
Classifier: Topic :: Communications :: Telephony
Classifier: License :: OSI Approved :: MIT License
Classifier: Programming Language :: Python :: 3
Classifier: Operating System :: OS Independent
Classifier: Programming Language :: Python :: 3
Classifier: Programming Language :: Python :: 3.5
Requires-Python: >=3.5
Requires-Dist: pyserial (>=3)
Requires-Dist: pathlib2 (>=2)
